{
 "method": "top-of-book sampled every 5 min from public venue APIs; spread = bps of mid; funding normalized to hourly then annualized (APR %). binance = CEX reference.",
 "symbols": [
  "BTC",
  "ETH",
  "SOL"
 ],
 "updated_at": "2026-07-07T05:09:01Z",
 "windows": {
  "d7": {
   "aster": {
    "BTC": {
     "funding_apr_pct": 9.027,
     "n": 1522,
     "spread_bps": 0.063,
     "spread_bps_max": 5.432,
     "spread_bps_min": 0.016
    },
    "ETH": {
     "funding_apr_pct": 7.986,
     "n": 1522,
     "spread_bps": 0.166,
     "spread_bps_max": 2.236,
     "spread_bps_min": 0.055
    },
    "SOL": {
     "funding_apr_pct": 8.132,
     "n": 1522,
     "spread_bps": 1.635,
     "spread_bps_max": 6.129,
     "spread_bps_min": 1.192
    }
   },
   "backpack": {
    "BTC": {
     "funding_apr_pct": 8.022,
     "n": 1522,
     "spread_bps": 0.021,
     "spread_bps_max": 1.604,
     "spread_bps_min": 0.015
    },
    "ETH": {
     "funding_apr_pct": 10.923,
     "n": 1522,
     "spread_bps": 0.065,
     "spread_bps_max": 3.043,
     "spread_bps_min": 0.055
    },
    "SOL": {
     "funding_apr_pct": 9.266,
     "n": 1522,
     "spread_bps": 1.242,
     "spread_bps_max": 2.487,
     "spread_bps_min": 1.193
    }
   },
   "binance": {
    "BTC": {
     "funding_apr_pct": 9.022,
     "n": 1521,
     "spread_bps": 0.016,
     "spread_bps_max": 0.214,
     "spread_bps_min": 0.016
    },
    "ETH": {
     "funding_apr_pct": 7.2,
     "n": 1521,
     "spread_bps": 0.058,
     "spread_bps_max": 0.12,
     "spread_bps_min": 0.055
    },
    "SOL": {
     "funding_apr_pct": 4.655,
     "n": 1521,
     "spread_bps": 1.235,
     "spread_bps_max": 2.475,
     "spread_bps_min": 1.193
    }
   },
   "edgex": {
    "BTC": {
     "funding_apr_pct": 10.95,
     "n": 1522,
     "spread_bps": 0.294,
     "spread_bps_max": 4.51,
     "spread_bps_min": 0.016
    },
    "ETH": {
     "funding_apr_pct": 10.95,
     "n": 1522,
     "spread_bps": 0.991,
     "spread_bps_max": 5.127,
     "spread_bps_min": 0.057
    },
    "SOL": {
     "funding_apr_pct": 8.769,
     "n": 1522,
     "spread_bps": 5.85,
     "spread_bps_max": 12.407,
     "spread_bps_min": 2.426
    }
   },
   "extended": {
    "BTC": {
     "funding_apr_pct": 11.255,
     "n": 1522,
     "spread_bps": 0.164,
     "spread_bps_max": 1.548,
     "spread_bps_min": 0.155
    },
    "ETH": {
     "funding_apr_pct": 3.575,
     "n": 1522,
     "spread_bps": 0.578,
     "spread_bps_max": 1.77,
     "spread_bps_min": 0.547
    },
    "SOL": {
     "funding_apr_pct": 5.431,
     "n": 1522,
     "spread_bps": 1.25,
     "spread_bps_max": 3.681,
     "spread_bps_min": 1.194
    }
   },
   "grvt": {
    "BTC": {
     "funding_apr_pct": 10.255,
     "n": 1522,
     "spread_bps": 0.018,
     "spread_bps_max": 0.813,
     "spread_bps_min": 0.015
    },
    "ETH": {
     "funding_apr_pct": 8.96,
     "n": 1522,
     "spread_bps": 0.062,
     "spread_bps_max": 1.474,
     "spread_bps_min": 0.055
    },
    "SOL": {
     "funding_apr_pct": 9.886,
     "n": 1522,
     "spread_bps": 1.239,
     "spread_bps_max": 3.814,
     "spread_bps_min": 1.193
    }
   },
   "hibachi": {
    "BTC": {
     "funding_apr_pct": -8.735,
     "n": 1522,
     "spread_bps": 0.09,
     "spread_bps_max": 3.612,
     "spread_bps_min": 0.016
    },
    "ETH": {
     "funding_apr_pct": -9.459,
     "n": 1522,
     "spread_bps": 1.242,
     "spread_bps_max": 23.719,
     "spread_bps_min": 0.055
    },
    "SOL": {
     "funding_apr_pct": -15.621,
     "n": 1522,
     "spread_bps": 2.231,
     "spread_bps_max": 13.732,
     "spread_bps_min": 0.12
    }
   },
   "hyperliquid": {
    "BTC": {
     "funding_apr_pct": 10.992,
     "n": 1522,
     "spread_bps": 0.169,
     "spread_bps_max": 1.658,
     "spread_bps_min": 0.155
    },
    "ETH": {
     "funding_apr_pct": 10.868,
     "n": 1522,
     "spread_bps": 0.593,
     "spread_bps_max": 2.933,
     "spread_bps_min": 0.547
    },
    "SOL": {
     "funding_apr_pct": 10.795,
     "n": 1522,
     "spread_bps": 0.171,
     "spread_bps_max": 2.846,
     "spread_bps_min": 0.119
    }
   },
   "lighter": {
    "BTC": {
     "funding_apr_pct": 10.244,
     "n": 1522,
     "spread_bps": 0.291,
     "spread_bps_max": 1.792,
     "spread_bps_min": 0.016
    },
    "ETH": {
     "funding_apr_pct": 10.286,
     "n": 1522,
     "spread_bps": 0.629,
     "spread_bps_max": 3.365,
     "spread_bps_min": 0.055
    },
    "SOL": {
     "funding_apr_pct": 6.435,
     "n": 1522,
     "spread_bps": 0.834,
     "spread_bps_max": 6.03,
     "spread_bps_min": 0.12
    }
   },
   "paradex": {
    "BTC": {
     "funding_apr_pct": 10.506,
     "n": 1522,
     "spread_bps": 3.602,
     "spread_bps_max": 273.066,
     "spread_bps_min": 0.016
    },
    "ETH": {
     "funding_apr_pct": 10.406,
     "n": 1522,
     "spread_bps": 8.115,
     "spread_bps_max": 272.953,
     "spread_bps_min": 0.115
    },
    "SOL": {
     "funding_apr_pct": 2.901,
     "n": 1522,
     "spread_bps": 48.98,
     "spread_bps_max": 978.137,
     "spread_bps_min": 1.404
    }
   }
  },
  "h24": {
   "aster": {
    "BTC": {
     "funding_apr_pct": 9.384,
     "n": 288,
     "spread_bps": 0.074,
     "spread_bps_max": 2.161,
     "spread_bps_min": 0.016
    },
    "ETH": {
     "funding_apr_pct": 8.252,
     "n": 288,
     "spread_bps": 0.236,
     "spread_bps_max": 2.111,
     "spread_bps_min": 0.055
    },
    "SOL": {
     "funding_apr_pct": 8.979,
     "n": 288,
     "spread_bps": 1.589,
     "spread_bps_max": 3.733,
     "spread_bps_min": 1.208
    }
   },
   "backpack": {
    "BTC": {
     "funding_apr_pct": 9.316,
     "n": 288,
     "spread_bps": 0.02,
     "spread_bps_max": 0.93,
     "spread_bps_min": 0.015
    },
    "ETH": {
     "funding_apr_pct": 10.835,
     "n": 288,
     "spread_bps": 0.063,
     "spread_bps_max": 1.094,
     "spread_bps_min": 0.055
    },
    "SOL": {
     "funding_apr_pct": 8.862,
     "n": 288,
     "spread_bps": 1.241,
     "spread_bps_max": 2.473,
     "spread_bps_min": 1.197
    }
   },
   "binance": {
    "BTC": {
     "funding_apr_pct": 10.119,
     "n": 287,
     "spread_bps": 0.016,
     "spread_bps_max": 0.065,
     "spread_bps_min": 0.016
    },
    "ETH": {
     "funding_apr_pct": 6.306,
     "n": 287,
     "spread_bps": 0.056,
     "spread_bps_max": 0.058,
     "spread_bps_min": 0.055
    },
    "SOL": {
     "funding_apr_pct": 6.683,
     "n": 287,
     "spread_bps": 1.232,
     "spread_bps_max": 1.262,
     "spread_bps_min": 1.199
    }
   },
   "edgex": {
    "BTC": {
     "funding_apr_pct": 10.95,
     "n": 288,
     "spread_bps": 0.307,
     "spread_bps_max": 1.642,
     "spread_bps_min": 0.032
    },
    "ETH": {
     "funding_apr_pct": 10.95,
     "n": 288,
     "spread_bps": 1.015,
     "spread_bps_max": 5.127,
     "spread_bps_min": 0.057
    },
    "SOL": {
     "funding_apr_pct": -0.575,
     "n": 288,
     "spread_bps": 5.54,
     "spread_bps_max": 8.692,
     "spread_bps_min": 2.507
    }
   },
   "extended": {
    "BTC": {
     "funding_apr_pct": 11.388,
     "n": 288,
     "spread_bps": 0.164,
     "spread_bps_max": 1.548,
     "spread_bps_min": 0.155
    },
    "ETH": {
     "funding_apr_pct": 3.851,
     "n": 288,
     "spread_bps": 0.563,
     "spread_bps_max": 0.578,
     "spread_bps_min": 0.547
    },
    "SOL": {
     "funding_apr_pct": 6.853,
     "n": 288,
     "spread_bps": 1.246,
     "spread_bps_max": 2.509,
     "spread_bps_min": 1.197
    }
   },
   "grvt": {
    "BTC": {
     "funding_apr_pct": 10.507,
     "n": 288,
     "spread_bps": 0.019,
     "spread_bps_max": 0.593,
     "spread_bps_min": 0.015
    },
    "ETH": {
     "funding_apr_pct": 6.651,
     "n": 288,
     "spread_bps": 0.067,
     "spread_bps_max": 0.972,
     "spread_bps_min": 0.055
    },
    "SOL": {
     "funding_apr_pct": 10.842,
     "n": 288,
     "spread_bps": 1.236,
     "spread_bps_max": 2.395,
     "spread_bps_min": 1.205
    }
   },
   "hibachi": {
    "BTC": {
     "funding_apr_pct": -10.117,
     "n": 288,
     "spread_bps": 0.115,
     "spread_bps_max": 3.358,
     "spread_bps_min": 0.016
    },
    "ETH": {
     "funding_apr_pct": -17.812,
     "n": 288,
     "spread_bps": 1.295,
     "spread_bps_max": 14.943,
     "spread_bps_min": 0.055
    },
    "SOL": {
     "funding_apr_pct": -4.438,
     "n": 288,
     "spread_bps": 2.28,
     "spread_bps_max": 12.332,
     "spread_bps_min": 0.122
    }
   },
   "hyperliquid": {
    "BTC": {
     "funding_apr_pct": 10.95,
     "n": 288,
     "spread_bps": 0.169,
     "spread_bps_max": 1.26,
     "spread_bps_min": 0.155
    },
    "ETH": {
     "funding_apr_pct": 10.95,
     "n": 288,
     "spread_bps": 0.585,
     "spread_bps_max": 2.266,
     "spread_bps_min": 0.547
    },
    "SOL": {
     "funding_apr_pct": 10.56,
     "n": 288,
     "spread_bps": 0.17,
     "spread_bps_max": 2.395,
     "spread_bps_min": 0.12
    }
   },
   "lighter": {
    "BTC": {
     "funding_apr_pct": 10.448,
     "n": 288,
     "spread_bps": 0.302,
     "spread_bps_max": 1.792,
     "spread_bps_min": 0.016
    },
    "ETH": {
     "funding_apr_pct": 10.329,
     "n": 288,
     "spread_bps": 0.649,
     "spread_bps_max": 1.649,
     "spread_bps_min": 0.055
    },
    "SOL": {
     "funding_apr_pct": 4.721,
     "n": 288,
     "spread_bps": 0.804,
     "spread_bps_max": 6.03,
     "spread_bps_min": 0.121
    }
   },
   "paradex": {
    "BTC": {
     "funding_apr_pct": 10.67,
     "n": 288,
     "spread_bps": 3.231,
     "spread_bps_max": 67.798,
     "spread_bps_min": 0.016
    },
    "ETH": {
     "funding_apr_pct": 10.394,
     "n": 288,
     "spread_bps": 5.491,
     "spread_bps_max": 28.257,
     "spread_bps_min": 0.115
    },
    "SOL": {
     "funding_apr_pct": 6.393,
     "n": 288,
     "spread_bps": 60.706,
     "spread_bps_max": 301.065,
     "spread_bps_min": 2.059
    }
   }
  }
 }
}
