{
 "method": "top-of-book sampled every 5 min from public venue APIs; spread = bps of mid; funding normalized to hourly then annualized (APR %). binance = CEX reference.",
 "symbols": [
  "BTC",
  "ETH",
  "SOL"
 ],
 "updated_at": "2026-07-12T17:09:02Z",
 "windows": {
  "d7": {
   "aster": {
    "BTC": {
     "funding_apr_pct": 5.476,
     "n": 1963,
     "spread_bps": 0.066,
     "spread_bps_max": 2.85,
     "spread_bps_min": 0.016
    },
    "ETH": {
     "funding_apr_pct": 5.205,
     "n": 1963,
     "spread_bps": 0.17,
     "spread_bps_max": 3.032,
     "spread_bps_min": 0.055
    },
    "SOL": {
     "funding_apr_pct": 4.882,
     "n": 1963,
     "spread_bps": 1.475,
     "spread_bps_max": 6.509,
     "spread_bps_min": 1.208
    }
   },
   "backpack": {
    "BTC": {
     "funding_apr_pct": 7.059,
     "n": 1963,
     "spread_bps": 0.017,
     "spread_bps_max": 0.947,
     "spread_bps_min": 0.015
    },
    "ETH": {
     "funding_apr_pct": 10.519,
     "n": 1963,
     "spread_bps": 0.058,
     "spread_bps_max": 1.094,
     "spread_bps_min": 0.055
    },
    "SOL": {
     "funding_apr_pct": 4.119,
     "n": 1963,
     "spread_bps": 1.274,
     "spread_bps_max": 2.628,
     "spread_bps_min": 1.197
    }
   },
   "binance": {
    "BTC": {
     "funding_apr_pct": 7.164,
     "n": 1961,
     "spread_bps": 0.016,
     "spread_bps_max": 0.469,
     "spread_bps_min": 0.016
    },
    "ETH": {
     "funding_apr_pct": 4.855,
     "n": 1961,
     "spread_bps": 0.057,
     "spread_bps_max": 1.266,
     "spread_bps_min": 0.055
    },
    "SOL": {
     "funding_apr_pct": 3.024,
     "n": 1961,
     "spread_bps": 1.267,
     "spread_bps_max": 1.319,
     "spread_bps_min": 1.199
    }
   },
   "edgex": {
    "BTC": {
     "funding_apr_pct": 10.95,
     "n": 1963,
     "spread_bps": 0.283,
     "spread_bps_max": 2.026,
     "spread_bps_min": 0.016
    },
    "ETH": {
     "funding_apr_pct": 10.401,
     "n": 1963,
     "spread_bps": 0.986,
     "spread_bps_max": 5.188,
     "spread_bps_min": 0.056
    },
    "SOL": {
     "funding_apr_pct": 6.909,
     "n": 1963,
     "spread_bps": 4.881,
     "spread_bps_max": 12.407,
     "spread_bps_min": 2.475
    }
   },
   "extended": {
    "BTC": {
     "funding_apr_pct": 9.849,
     "n": 1963,
     "spread_bps": 0.161,
     "spread_bps_max": 1.61,
     "spread_bps_min": 0.155
    },
    "ETH": {
     "funding_apr_pct": 2.588,
     "n": 1963,
     "spread_bps": 0.567,
     "spread_bps_max": 1.683,
     "spread_bps_min": 0.547
    },
    "SOL": {
     "funding_apr_pct": 7.503,
     "n": 1963,
     "spread_bps": 1.272,
     "spread_bps_max": 2.607,
     "spread_bps_min": 1.197
    }
   },
   "grvt": {
    "BTC": {
     "funding_apr_pct": 9.806,
     "n": 1963,
     "spread_bps": 0.017,
     "spread_bps_max": 0.593,
     "spread_bps_min": 0.015
    },
    "ETH": {
     "funding_apr_pct": 8.519,
     "n": 1963,
     "spread_bps": 0.068,
     "spread_bps_max": 3.204,
     "spread_bps_min": 0.055
    },
    "SOL": {
     "funding_apr_pct": 10.215,
     "n": 1963,
     "spread_bps": 1.271,
     "spread_bps_max": 2.592,
     "spread_bps_min": 1.205
    }
   },
   "hibachi": {
    "BTC": {
     "funding_apr_pct": -6.323,
     "n": 1952,
     "spread_bps": 0.068,
     "spread_bps_max": 3.358,
     "spread_bps_min": 0.016
    },
    "ETH": {
     "funding_apr_pct": -0.299,
     "n": 1952,
     "spread_bps": 0.569,
     "spread_bps_max": 14.943,
     "spread_bps_min": 0.055
    },
    "SOL": {
     "funding_apr_pct": -5.887,
     "n": 1952,
     "spread_bps": 1.037,
     "spread_bps_max": 12.332,
     "spread_bps_min": 0.122
    }
   },
   "hyperliquid": {
    "BTC": {
     "funding_apr_pct": 10.947,
     "n": 1962,
     "spread_bps": 0.168,
     "spread_bps_max": 3.449,
     "spread_bps_min": 0.155
    },
    "ETH": {
     "funding_apr_pct": 10.915,
     "n": 1962,
     "spread_bps": 0.579,
     "spread_bps_max": 4.029,
     "spread_bps_min": 0.547
    },
    "SOL": {
     "funding_apr_pct": 9.454,
     "n": 1962,
     "spread_bps": 0.17,
     "spread_bps_max": 2.965,
     "spread_bps_min": 0.12
    }
   },
   "lighter": {
    "BTC": {
     "funding_apr_pct": 7.772,
     "n": 1963,
     "spread_bps": 0.34,
     "spread_bps_max": 1.792,
     "spread_bps_min": 0.016
    },
    "ETH": {
     "funding_apr_pct": 10.059,
     "n": 1963,
     "spread_bps": 0.633,
     "spread_bps_max": 2.476,
     "spread_bps_min": 0.055
    },
    "SOL": {
     "funding_apr_pct": 5.439,
     "n": 1963,
     "spread_bps": 0.817,
     "spread_bps_max": 6.03,
     "spread_bps_min": 0.121
    }
   },
   "paradex": {
    "BTC": {
     "funding_apr_pct": 9.58,
     "n": 1963,
     "spread_bps": 2.696,
     "spread_bps_max": 67.798,
     "spread_bps_min": 0.016
    },
    "ETH": {
     "funding_apr_pct": 9.79,
     "n": 1963,
     "spread_bps": 6.322,
     "spread_bps_max": 244.379,
     "spread_bps_min": 0.057
    },
    "SOL": {
     "funding_apr_pct": 6.319,
     "n": 1963,
     "spread_bps": 24.301,
     "spread_bps_max": 674.824,
     "spread_bps_min": 0.126
    }
   }
  },
  "h24": {
   "aster": {
    "BTC": {
     "funding_apr_pct": 5.413,
     "n": 260,
     "spread_bps": 0.036,
     "spread_bps_max": 1.047,
     "spread_bps_min": 0.016
    },
    "ETH": {
     "funding_apr_pct": 2.028,
     "n": 260,
     "spread_bps": 0.087,
     "spread_bps_max": 1.6,
     "spread_bps_min": 0.055
    },
    "SOL": {
     "funding_apr_pct": 0.72,
     "n": 260,
     "spread_bps": 1.329,
     "spread_bps_max": 3.944,
     "spread_bps_min": 1.278
    }
   },
   "backpack": {
    "BTC": {
     "funding_apr_pct": 5.195,
     "n": 260,
     "spread_bps": 0.017,
     "spread_bps_max": 0.439,
     "spread_bps_min": 0.016
    },
    "ETH": {
     "funding_apr_pct": 8.467,
     "n": 260,
     "spread_bps": 0.056,
     "spread_bps_max": 0.168,
     "spread_bps_min": 0.055
    },
    "SOL": {
     "funding_apr_pct": 3.219,
     "n": 260,
     "spread_bps": 1.304,
     "spread_bps_max": 2.628,
     "spread_bps_min": 1.279
    }
   },
   "binance": {
    "BTC": {
     "funding_apr_pct": 6.556,
     "n": 260,
     "spread_bps": 0.016,
     "spread_bps_max": 0.141,
     "spread_bps_min": 0.016
    },
    "ETH": {
     "funding_apr_pct": 1.99,
     "n": 260,
     "spread_bps": 0.055,
     "spread_bps_max": 0.056,
     "spread_bps_min": 0.055
    },
    "SOL": {
     "funding_apr_pct": 0.834,
     "n": 260,
     "spread_bps": 1.299,
     "spread_bps_max": 1.319,
     "spread_bps_min": 1.278
    }
   },
   "edgex": {
    "BTC": {
     "funding_apr_pct": 10.95,
     "n": 260,
     "spread_bps": 0.248,
     "spread_bps_max": 0.439,
     "spread_bps_min": 0.016
    },
    "ETH": {
     "funding_apr_pct": 10.95,
     "n": 260,
     "spread_bps": 0.982,
     "spread_bps_max": 5.188,
     "spread_bps_min": 0.056
    },
    "SOL": {
     "funding_apr_pct": -6.796,
     "n": 260,
     "spread_bps": 4.958,
     "spread_bps_max": 6.551,
     "spread_bps_min": 2.617
    }
   },
   "extended": {
    "BTC": {
     "funding_apr_pct": 4.798,
     "n": 260,
     "spread_bps": 0.156,
     "spread_bps_max": 0.157,
     "spread_bps_min": 0.155
    },
    "ETH": {
     "funding_apr_pct": 2.911,
     "n": 260,
     "spread_bps": 0.563,
     "spread_bps_max": 1.669,
     "spread_bps_min": 0.548
    },
    "SOL": {
     "funding_apr_pct": 11.034,
     "n": 260,
     "spread_bps": 1.304,
     "spread_bps_max": 2.607,
     "spread_bps_min": 1.279
    }
   },
   "grvt": {
    "BTC": {
     "funding_apr_pct": 10.95,
     "n": 260,
     "spread_bps": 0.018,
     "spread_bps_max": 0.529,
     "spread_bps_min": 0.016
    },
    "ETH": {
     "funding_apr_pct": 10.95,
     "n": 260,
     "spread_bps": 0.062,
     "spread_bps_max": 1.106,
     "spread_bps_min": 0.055
    },
    "SOL": {
     "funding_apr_pct": 10.95,
     "n": 260,
     "spread_bps": 1.298,
     "spread_bps_max": 1.319,
     "spread_bps_min": 1.278
    }
   },
   "hibachi": {
    "BTC": {
     "funding_apr_pct": -7.958,
     "n": 260,
     "spread_bps": 0.03,
     "spread_bps_max": 1.089,
     "spread_bps_min": 0.016
    },
    "ETH": {
     "funding_apr_pct": -3.736,
     "n": 260,
     "spread_bps": 0.181,
     "spread_bps_max": 1.706,
     "spread_bps_min": 0.055
    },
    "SOL": {
     "funding_apr_pct": -9.205,
     "n": 260,
     "spread_bps": 0.492,
     "spread_bps_max": 2.501,
     "spread_bps_min": 0.128
    }
   },
   "hyperliquid": {
    "BTC": {
     "funding_apr_pct": 10.95,
     "n": 260,
     "spread_bps": 0.156,
     "spread_bps_max": 0.157,
     "spread_bps_min": 0.155
    },
    "ETH": {
     "funding_apr_pct": 10.95,
     "n": 260,
     "spread_bps": 0.555,
     "spread_bps_max": 1.107,
     "spread_bps_min": 0.547
    },
    "SOL": {
     "funding_apr_pct": 9.888,
     "n": 260,
     "spread_bps": 0.144,
     "spread_bps_max": 1.177,
     "spread_bps_min": 0.128
    }
   },
   "lighter": {
    "BTC": {
     "funding_apr_pct": 7.436,
     "n": 260,
     "spread_bps": 0.369,
     "spread_bps_max": 1.08,
     "spread_bps_min": 0.016
    },
    "ETH": {
     "funding_apr_pct": 10.482,
     "n": 260,
     "spread_bps": 0.617,
     "spread_bps_max": 1.846,
     "spread_bps_min": 0.055
    },
    "SOL": {
     "funding_apr_pct": 9.441,
     "n": 260,
     "spread_bps": 0.788,
     "spread_bps_max": 1.712,
     "spread_bps_min": 0.128
    }
   },
   "paradex": {
    "BTC": {
     "funding_apr_pct": 8.558,
     "n": 260,
     "spread_bps": 2.474,
     "spread_bps_max": 4.126,
     "spread_bps_min": 0.016
    },
    "ETH": {
     "funding_apr_pct": 10.606,
     "n": 260,
     "spread_bps": 6.365,
     "spread_bps_max": 12.369,
     "spread_bps_min": 1.319
    },
    "SOL": {
     "funding_apr_pct": 7.921,
     "n": 260,
     "spread_bps": 4.101,
     "spread_bps_max": 7.962,
     "spread_bps_min": 0.129
    }
   }
  }
 }
}
