{
 "method": "top-of-book sampled every 5 min from public venue APIs; spread = bps of mid; funding normalized to hourly then annualized (APR %). binance = CEX reference.",
 "symbols": [
  "BTC",
  "ETH",
  "SOL"
 ],
 "updated_at": "2026-07-10T21:09:01Z",
 "windows": {
  "d7": {
   "aster": {
    "BTC": {
     "funding_apr_pct": 6.579,
     "n": 2016,
     "spread_bps": 0.067,
     "spread_bps_max": 2.85,
     "spread_bps_min": 0.016
    },
    "ETH": {
     "funding_apr_pct": 6.4,
     "n": 2016,
     "spread_bps": 0.174,
     "spread_bps_max": 3.032,
     "spread_bps_min": 0.055
    },
    "SOL": {
     "funding_apr_pct": 6.865,
     "n": 2016,
     "spread_bps": 1.574,
     "spread_bps_max": 6.509,
     "spread_bps_min": 1.192
    }
   },
   "backpack": {
    "BTC": {
     "funding_apr_pct": 7.839,
     "n": 2016,
     "spread_bps": 0.018,
     "spread_bps_max": 1.604,
     "spread_bps_min": 0.015
    },
    "ETH": {
     "funding_apr_pct": 10.851,
     "n": 2016,
     "spread_bps": 0.059,
     "spread_bps_max": 1.243,
     "spread_bps_min": 0.055
    },
    "SOL": {
     "funding_apr_pct": 6.1,
     "n": 2016,
     "spread_bps": 1.257,
     "spread_bps_max": 2.622,
     "spread_bps_min": 1.193
    }
   },
   "binance": {
    "BTC": {
     "funding_apr_pct": 8.293,
     "n": 2014,
     "spread_bps": 0.016,
     "spread_bps_max": 0.469,
     "spread_bps_min": 0.016
    },
    "ETH": {
     "funding_apr_pct": 5.96,
     "n": 2014,
     "spread_bps": 0.057,
     "spread_bps_max": 1.266,
     "spread_bps_min": 0.055
    },
    "SOL": {
     "funding_apr_pct": 4.059,
     "n": 2014,
     "spread_bps": 1.25,
     "spread_bps_max": 1.31,
     "spread_bps_min": 1.193
    }
   },
   "edgex": {
    "BTC": {
     "funding_apr_pct": 10.95,
     "n": 2016,
     "spread_bps": 0.29,
     "spread_bps_max": 4.51,
     "spread_bps_min": 0.016
    },
    "ETH": {
     "funding_apr_pct": 10.415,
     "n": 2016,
     "spread_bps": 0.996,
     "spread_bps_max": 5.127,
     "spread_bps_min": 0.056
    },
    "SOL": {
     "funding_apr_pct": 9.304,
     "n": 2016,
     "spread_bps": 5.309,
     "spread_bps_max": 12.407,
     "spread_bps_min": 2.426
    }
   },
   "extended": {
    "BTC": {
     "funding_apr_pct": 10.956,
     "n": 2016,
     "spread_bps": 0.162,
     "spread_bps_max": 1.61,
     "spread_bps_min": 0.155
    },
    "ETH": {
     "funding_apr_pct": 3.156,
     "n": 2016,
     "spread_bps": 0.569,
     "spread_bps_max": 1.707,
     "spread_bps_min": 0.547
    },
    "SOL": {
     "funding_apr_pct": 5.021,
     "n": 2016,
     "spread_bps": 1.259,
     "spread_bps_max": 3.679,
     "spread_bps_min": 1.194
    }
   },
   "grvt": {
    "BTC": {
     "funding_apr_pct": 9.533,
     "n": 2016,
     "spread_bps": 0.017,
     "spread_bps_max": 0.593,
     "spread_bps_min": 0.015
    },
    "ETH": {
     "funding_apr_pct": 8.252,
     "n": 2016,
     "spread_bps": 0.068,
     "spread_bps_max": 3.204,
     "spread_bps_min": 0.055
    },
    "SOL": {
     "funding_apr_pct": 9.817,
     "n": 2016,
     "spread_bps": 1.255,
     "spread_bps_max": 2.592,
     "spread_bps_min": 1.193
    }
   },
   "hibachi": {
    "BTC": {
     "funding_apr_pct": -5.59,
     "n": 2005,
     "spread_bps": 0.068,
     "spread_bps_max": 3.358,
     "spread_bps_min": 0.016
    },
    "ETH": {
     "funding_apr_pct": -1.034,
     "n": 2005,
     "spread_bps": 0.809,
     "spread_bps_max": 16.555,
     "spread_bps_min": 0.055
    },
    "SOL": {
     "funding_apr_pct": -9.052,
     "n": 2005,
     "spread_bps": 1.437,
     "spread_bps_max": 12.332,
     "spread_bps_min": 0.12
    }
   },
   "hyperliquid": {
    "BTC": {
     "funding_apr_pct": 10.947,
     "n": 2016,
     "spread_bps": 0.169,
     "spread_bps_max": 3.449,
     "spread_bps_min": 0.155
    },
    "ETH": {
     "funding_apr_pct": 10.937,
     "n": 2016,
     "spread_bps": 0.58,
     "spread_bps_max": 4.029,
     "spread_bps_min": 0.547
    },
    "SOL": {
     "funding_apr_pct": 9.69,
     "n": 2016,
     "spread_bps": 0.17,
     "spread_bps_max": 2.965,
     "spread_bps_min": 0.119
    }
   },
   "lighter": {
    "BTC": {
     "funding_apr_pct": 9.037,
     "n": 2016,
     "spread_bps": 0.31,
     "spread_bps_max": 1.792,
     "spread_bps_min": 0.016
    },
    "ETH": {
     "funding_apr_pct": 10.168,
     "n": 2016,
     "spread_bps": 0.633,
     "spread_bps_max": 2.476,
     "spread_bps_min": 0.055
    },
    "SOL": {
     "funding_apr_pct": 4.68,
     "n": 2016,
     "spread_bps": 0.822,
     "spread_bps_max": 6.03,
     "spread_bps_min": 0.12
    }
   },
   "paradex": {
    "BTC": {
     "funding_apr_pct": 10.093,
     "n": 2016,
     "spread_bps": 2.934,
     "spread_bps_max": 67.798,
     "spread_bps_min": 0.016
    },
    "ETH": {
     "funding_apr_pct": 9.936,
     "n": 2016,
     "spread_bps": 6.367,
     "spread_bps_max": 244.379,
     "spread_bps_min": 0.057
    },
    "SOL": {
     "funding_apr_pct": 4.534,
     "n": 2016,
     "spread_bps": 27.404,
     "spread_bps_max": 674.824,
     "spread_bps_min": 0.126
    }
   }
  },
  "h24": {
   "aster": {
    "BTC": {
     "funding_apr_pct": 6.667,
     "n": 288,
     "spread_bps": 0.047,
     "spread_bps_max": 1.739,
     "spread_bps_min": 0.016
    },
    "ETH": {
     "funding_apr_pct": 4.628,
     "n": 288,
     "spread_bps": 0.129,
     "spread_bps_max": 2.92,
     "spread_bps_min": 0.055
    },
    "SOL": {
     "funding_apr_pct": 6.758,
     "n": 288,
     "spread_bps": 1.336,
     "spread_bps_max": 3.846,
     "spread_bps_min": 1.256
    }
   },
   "backpack": {
    "BTC": {
     "funding_apr_pct": 4.908,
     "n": 288,
     "spread_bps": 0.016,
     "spread_bps_max": 0.016,
     "spread_bps_min": 0.016
    },
    "ETH": {
     "funding_apr_pct": 10.899,
     "n": 288,
     "spread_bps": 0.057,
     "spread_bps_max": 0.113,
     "spread_bps_min": 0.055
    },
    "SOL": {
     "funding_apr_pct": 1.629,
     "n": 288,
     "spread_bps": 1.274,
     "spread_bps_max": 1.293,
     "spread_bps_min": 1.257
    }
   },
   "binance": {
    "BTC": {
     "funding_apr_pct": 9.066,
     "n": 287,
     "spread_bps": 0.016,
     "spread_bps_max": 0.11,
     "spread_bps_min": 0.016
    },
    "ETH": {
     "funding_apr_pct": 5.46,
     "n": 287,
     "spread_bps": 0.056,
     "spread_bps_max": 0.058,
     "spread_bps_min": 0.055
    },
    "SOL": {
     "funding_apr_pct": 5.057,
     "n": 287,
     "spread_bps": 1.274,
     "spread_bps_max": 1.293,
     "spread_bps_min": 1.256
    }
   },
   "edgex": {
    "BTC": {
     "funding_apr_pct": 10.95,
     "n": 288,
     "spread_bps": 0.282,
     "spread_bps_max": 1.971,
     "spread_bps_min": 0.016
    },
    "ETH": {
     "funding_apr_pct": 10.95,
     "n": 288,
     "spread_bps": 0.967,
     "spread_bps_max": 2.29,
     "spread_bps_min": 0.056
    },
    "SOL": {
     "funding_apr_pct": 10.95,
     "n": 288,
     "spread_bps": 4.686,
     "spread_bps_max": 10.127,
     "spread_bps_min": 2.573
    }
   },
   "extended": {
    "BTC": {
     "funding_apr_pct": 9.283,
     "n": 288,
     "spread_bps": 0.159,
     "spread_bps_max": 0.624,
     "spread_bps_min": 0.155
    },
    "ETH": {
     "funding_apr_pct": 0.502,
     "n": 288,
     "spread_bps": 0.565,
     "spread_bps_max": 1.151,
     "spread_bps_min": 0.555
    },
    "SOL": {
     "funding_apr_pct": 7.595,
     "n": 288,
     "spread_bps": 1.279,
     "spread_bps_max": 2.573,
     "spread_bps_min": 1.258
    }
   },
   "grvt": {
    "BTC": {
     "funding_apr_pct": 10.95,
     "n": 288,
     "spread_bps": 0.016,
     "spread_bps_max": 0.016,
     "spread_bps_min": 0.016
    },
    "ETH": {
     "funding_apr_pct": 10.95,
     "n": 288,
     "spread_bps": 0.059,
     "spread_bps_max": 0.502,
     "spread_bps_min": 0.055
    },
    "SOL": {
     "funding_apr_pct": 10.95,
     "n": 288,
     "spread_bps": 1.274,
     "spread_bps_max": 1.293,
     "spread_bps_min": 1.257
    }
   },
   "hibachi": {
    "BTC": {
     "funding_apr_pct": -0.52,
     "n": 288,
     "spread_bps": 0.054,
     "spread_bps_max": 0.798,
     "spread_bps_min": 0.016
    },
    "ETH": {
     "funding_apr_pct": -2.458,
     "n": 288,
     "spread_bps": 0.355,
     "spread_bps_max": 2.117,
     "spread_bps_min": 0.055
    },
    "SOL": {
     "funding_apr_pct": 5.426,
     "n": 288,
     "spread_bps": 0.655,
     "spread_bps_max": 3.964,
     "spread_bps_min": 0.126
    }
   },
   "hyperliquid": {
    "BTC": {
     "funding_apr_pct": 10.95,
     "n": 288,
     "spread_bps": 0.163,
     "spread_bps_max": 2.17,
     "spread_bps_min": 0.155
    },
    "ETH": {
     "funding_apr_pct": 10.845,
     "n": 288,
     "spread_bps": 0.568,
     "spread_bps_max": 2.236,
     "spread_bps_min": 0.554
    },
    "SOL": {
     "funding_apr_pct": 10.882,
     "n": 288,
     "spread_bps": 0.157,
     "spread_bps_max": 2.52,
     "spread_bps_min": 0.126
    }
   },
   "lighter": {
    "BTC": {
     "funding_apr_pct": 9.715,
     "n": 288,
     "spread_bps": 0.373,
     "spread_bps_max": 1.332,
     "spread_bps_min": 0.016
    },
    "ETH": {
     "funding_apr_pct": 10.345,
     "n": 288,
     "spread_bps": 0.541,
     "spread_bps_max": 1.504,
     "spread_bps_min": 0.056
    },
    "SOL": {
     "funding_apr_pct": 9.265,
     "n": 288,
     "spread_bps": 0.823,
     "spread_bps_max": 2.041,
     "spread_bps_min": 0.126
    }
   },
   "paradex": {
    "BTC": {
     "funding_apr_pct": 10.6,
     "n": 288,
     "spread_bps": 1.94,
     "spread_bps_max": 17.995,
     "spread_bps_min": 0.016
    },
    "ETH": {
     "funding_apr_pct": 9.939,
     "n": 288,
     "spread_bps": 6.868,
     "spread_bps_max": 160.662,
     "spread_bps_min": 0.631
    },
    "SOL": {
     "funding_apr_pct": 9.007,
     "n": 288,
     "spread_bps": 12.265,
     "spread_bps_max": 180.385,
     "spread_bps_min": 0.126
    }
   }
  }
 }
}
